libla/__init__.py
libla/matrix.py
libla/rank_decomposition.py
libla/vect.py
libla-0.0.2.dist-info/WHEEL
libla-0.0.2.dist-info/METADATA
libla-0.0.2.dist-info/RECORD
