Metadata-Version: 2.1
Name: libla
Version: 0.0.2
Summary: A Linear Algebra Library for Python/numpy
Author: Heinrich Hartmann
Author-email: heinrich@heinrichhartmann.com
Requires-Python: >=3.8,<4.0
Classifier: Programming Language :: Python :: 3
Classifier: Programming Language :: Python :: 3.8
Classifier: Programming Language :: Python :: 3.9
Requires-Dist: matplotlib (>=3.3.4,<4.0.0)
Requires-Dist: numpy (>=1.20.1,<2.0.0)
Requires-Dist: pandas (>=1.2.2,<2.0.0)
Requires-Dist: pytest (>=6.2.2,<7.0.0)
Requires-Dist: scipy (>=1.6.1,<2.0.0)
